wordlecli/__init__.py
wordlecli/cli.py
wordlecli/wordle.py
wordlecli/words.py
wordlecli-0.2.6.dist-info/entry_points.txt
wordlecli-0.2.6.dist-info/LICENSE
wordlecli-0.2.6.dist-info/WHEEL
wordlecli-0.2.6.dist-info/METADATA
wordlecli-0.2.6.dist-info/RECORD
