Metadata-Version: 2.1
Name: wordlecli
Version: 0.2.6
Summary: wordle, but in the command line
License: MIT
Author: dotzenith
Requires-Python: >=3.9,<4.0
Classifier: License :: OSI Approved :: MIT License
Classifier: Programming Language :: Python :: 3
Classifier: Programming Language :: Python :: 3.9
Classifier: Programming Language :: Python :: 3.10
Classifier: Programming Language :: Python :: 3.11
Requires-Dist: DateTime (>=4.4,<5.0)
Requires-Dist: pyperclip (>=1.8.2,<2.0.0)
Requires-Dist: rich (>=11.2.0,<12.0.0)
Requires-Dist: typer (>=0.4.0,<0.5.0)
